nasdaq/__init__.py
nasdaq/cli.py
nasdaq/data_processing.py
nasdaq/nasdaq.py
nasdaq-0.1.0.dist-info/licenses/LICENSE
nasdaq-0.1.0.dist-info/METADATA
nasdaq-0.1.0.dist-info/WHEEL
nasdaq-0.1.0.dist-info/entry_points.txt
nasdaq-0.1.0.dist-info/top_level.txt
nasdaq-0.1.0.dist-info/RECORD
